README.md
setup.cfg
setup.py
distdj/Binomialdistribution.py
distdj/Gaussiandistribution.py
distdj/Generaldistribution.py
distdj/__init__.py
distdj.egg-info/PKG-INFO
distdj.egg-info/SOURCES.txt
distdj.egg-info/dependency_links.txt
distdj.egg-info/not-zip-safe
distdj.egg-info/top_level.txt